{
  "M1.1_两位数除以一位数": {
    "score": 0,
    "last_change": 0,
    "updated_at": ""
  },
  "M1.2_三位数除以一位数": {
    "score": 0,
    "last_change": 0,
    "updated_at": ""
  },
  "M1.3_商中间有0的除法": {
    "score": 0,
    "last_change": 0,
    "updated_at": ""
  },
  "M1.4_有余数的除法": {
    "score": 0,
    "last_change": 0,
    "updated_at": ""
  },
  "M2.1_轴对称图形": {
    "score": 0,
    "last_change": 0,
    "updated_at": ""
  },
  "M2.2_平移": {
    "score": 0,
    "last_change": 0,
    "updated_at": ""
  },
  "M2.3_旋转": {
    "score": 0,
    "last_change": 0,
    "updated_at": ""
  },
  "M3.1_两位数乘两位数": {
    "score": 0,
    "last_change": 0,
    "updated_at": ""
  },
  "M3.2_进位乘法": {
    "score": 0,
    "last_change": 0,
    "updated_at": ""
  },
  "M3.3_末尾有0的乘法": {
    "score": 0,
    "last_change": 0,
    "updated_at": ""
  },
  "M4.1_质量单位认识": {
    "score": 0,
    "last_change": 0,
    "updated_at": ""
  },
  "M4.2_质量单位换算": {
    "score": 0,
    "last_change": 0,
    "updated_at": ""
  },
  "M4.3_质量实际感知": {
    "score": 0,
    "last_change": 0,
    "updated_at": ""
  },
  "M4.4_质量解决问题": {
    "score": 0,
    "last_change": 0,
    "updated_at": ""
  },
  "M5.1_面积概念": {
    "score": 0,
    "last_change": 0,
    "updated_at": ""
  },
  "M5.2_长方形正方形面积公式": {
    "score": 0,
    "last_change": 0,
    "updated_at": ""
  },
  "M5.3_面积单位换算": {
    "score": 0,
    "last_change": 0,
    "updated_at": ""
  },
  "M6.1_分数的意义": {
    "score": 0,
    "last_change": 0,
    "updated_at": ""
  },
  "M6.2_分数大小比较": {
    "score": 0,
    "last_change": 0,
    "updated_at": ""
  },
  "M6.3_同分母分数加减": {
    "score": 0,
    "last_change": 0,
    "updated_at": ""
  },
  "M6.4_分数的简单应用": {
    "score": 0,
    "last_change": 0,
    "updated_at": ""
  },
  "M7.1_分类统计": {
    "score": 0,
    "last_change": 0,
    "updated_at": ""
  },
  "M7.2_简单图表": {
    "score": 0,
    "last_change": 0,
    "updated_at": ""
  },
  "M7.3_数据分析和决策": {
    "score": 0,
    "last_change": 0,
    "updated_at": ""
  },
  "G1_一般现在时": {
    "score": 0,
    "last_change": 0,
    "updated_at": ""
  },
  "G2_现在进行时": {
    "score": 0,
    "last_change": 0,
    "updated_at": ""
  },
  "G3_一般过去时": {
    "score": 0,
    "last_change": 0,
    "updated_at": ""
  },
  "G4_一般将来时": {
    "score": 0,
    "last_change": 0,
    "updated_at": ""
  },
  "G5_比较级和最高级": {
    "score": 0,
    "last_change": 0,
    "updated_at": ""
  },
  "G6_情态动词": {
    "score": 0,
    "last_change": 0,
    "updated_at": ""
  },
  "G7_介词": {
    "score": 0,
    "last_change": 0,
    "updated_at": ""
  },
  "G8_连词": {
    "score": 0,
    "last_change": 0,
    "updated_at": ""
  },
  "G9_疑问句": {
    "score": 0,
    "last_change": 0,
    "updated_at": ""
  },
  "G10_综合复习": {
    "score": 0,
    "last_change": 0,
    "updated_at": ""
  }
}